power_markets/__init__.py
power_markets/__main__.py
power_markets/catalog.yaml
power_markets/cli.py
power_markets/exceptions.py
power_markets/help.py
power_markets/settings.py
power_markets/utils.py
power_markets/countries/__init__.py
power_markets/countries/Greece/__init__.py
power_markets/countries/Greece/admie.py
power_markets/datasets/availability_factors/EL/af.csv
power_markets/datasets/capacity/EL/available.csv
power_markets/datasets/flows/EL/exports.csv
power_markets/datasets/flows/EL/imports.csv
power_markets/datasets/generation/EL/RES.csv
power_markets/datasets/generation/EL/committed.csv
power_markets/datasets/hydro/EL/reservoirs.csv
power_markets/datasets/load/EL/load.csv
power_markets/datasets/load/EL/reserves.csv
power_markets/datasets/ntc/EL/exports.csv
power_markets/datasets/ntc/EL/imports.csv
power_markets/datasets/plants/EL/plants.csv
power_markets/datasets/prices/EL/lignite.csv
power_markets/datasets/prices/EL/ngas.csv
power_markets/datasets/prices/EU/carbon.csv
power_markets/datasets/prices/EU/coal.csv
power_markets/datasets/prices/EU/ngas.csv
power_markets/datasets/prices/EU/oil.csv
power_markets-0.1.dist-info/LICENSE
power_markets-0.1.dist-info/METADATA
power_markets-0.1.dist-info/WHEEL
power_markets-0.1.dist-info/entry_points.txt
power_markets-0.1.dist-info/top_level.txt
power_markets-0.1.dist-info/RECORD
