Metadata-Version: 2.1
Name: power-markets
Version: 0.1
Summary: Power market datasets
Home-page: https://github.com/hebes-io/power-markets
Classifier: Development Status :: 4 - Beta
Classifier: Intended Audience :: Science/Research
Classifier: Intended Audience :: Developers
Classifier: License :: OSI Approved :: MIT License
Classifier: Programming Language :: Python :: 3
Classifier: Programming Language :: Python :: 3.7
Classifier: Programming Language :: Python :: 3.8
Classifier: Programming Language :: Python :: 3.9
Classifier: Programming Language :: Python :: 3.10
Classifier: Topic :: Scientific/Engineering
Classifier: Operating System :: OS Independent
Requires-Python: >=3.7
License-File: LICENSE
Requires-Dist: click (>=8.0.0)
Requires-Dist: intake (>=0.6.8)
Requires-Dist: pandas (>=2.0.0)
Requires-Dist: tqdm (>=4.65.0)
Requires-Dist: xlrd (>=2.0.1)
